nbdev_hello_world/__init__.py
nbdev_hello_world/_modidx.py
nbdev_hello_world/core.py
nbdev_hello_world/dice.py
nbdev_hello_dice-0.0.2.dist-info/LICENSE
nbdev_hello_dice-0.0.2.dist-info/METADATA
nbdev_hello_dice-0.0.2.dist-info/WHEEL
nbdev_hello_dice-0.0.2.dist-info/entry_points.txt
nbdev_hello_dice-0.0.2.dist-info/top_level.txt
nbdev_hello_dice-0.0.2.dist-info/RECORD
