Metadata-Version: 2.1
Name: nbdev-hello-dice
Version: 0.0.2
Summary: Hello Worlddice throwing setup process for nbdev
Home-page: https://github.com/cooperrc/nbdev-hello-world
Author: Ryan C. Cooper
Author-email: ryan.c.cooper@uconn.edu
License: Apache Software License 2.0
Keywords: nbdev jupyter notebook python
Classifier: Development Status :: 4 - Beta
Classifier: Intended Audience :: Developers
Classifier: Natural Language :: English
Classifier: Programming Language :: Python :: 3.7
Classifier: Programming Language :: Python :: 3.8
Classifier: Programming Language :: Python :: 3.9
Classifier: Programming Language :: Python :: 3.10
Classifier: License :: OSI Approved :: Apache Software License
Requires-Python: >=3.7
License-File: LICENSE
Requires-Dist: numpy
Provides-Extra: dev
